qgate_graph/__init__.py
qgate_graph/circle_queue.py
qgate_graph/file_marker.py
qgate_graph/graph_base.py
qgate_graph/graph_executor.py
qgate_graph/graph_performance.py
qgate_graph/graph_performance_csv.py
qgate_graph/graph_performance_txt.py
qgate_graph/graph_setup.py
qgate_graph/percentile_item.py
qgate_graph/version.py
qgate_graph-1.4.30.dist-info/LICENSE
qgate_graph-1.4.30.dist-info/METADATA
qgate_graph-1.4.30.dist-info/WHEEL
qgate_graph-1.4.30.dist-info/top_level.txt
qgate_graph-1.4.30.dist-info/RECORD
