Metadata-Version: 2.1
Name: qgate_graph
Version: 1.4.30
Summary: Generate graphs based on outputs from Quality Gate
Author-email: Jiri Steuer <steuer.jiri@gmail.com>
Maintainer-email: Jiri Steuer <steuer.jiri@gmail.com>
License: MIT
Project-URL: homepage, https://github.com/george0st/qgate-graph/
Project-URL: repository, https://pypi.org/project/qgate_graph/
Keywords: Quality,QualityGate,Graph
Classifier: Development Status :: 5 - Production/Stable
Classifier: Intended Audience :: Developers
Classifier: License :: OSI Approved :: Apache Software License
Classifier: Operating System :: POSIX :: Linux
Classifier: Operating System :: Microsoft :: Windows
Classifier: Operating System :: MacOS
Classifier: Programming Language :: Python :: 3
Classifier: Programming Language :: Python :: 3.6
Classifier: Programming Language :: Python :: 3.7
Classifier: Programming Language :: Python :: 3.8
Classifier: Programming Language :: Python :: 3.9
Classifier: Programming Language :: Python :: 3.10
Classifier: Programming Language :: Python :: 3.11
Classifier: Programming Language :: Python :: 3 :: Only
Classifier: Programming Language :: Python
Classifier: Topic :: Software Development :: Libraries :: Python Modules
Classifier: Topic :: Software Development :: Libraries
Requires-Python: >=3.6
License-File: LICENSE
Requires-Dist: click~=8.1
Requires-Dist: matplotlib<=3.9.2,>=3.5.0
Requires-Dist: numpy<=2.1.3,>=1.24.3
Requires-Dist: prettytable==3.11.0
Provides-Extra: dev
Requires-Dist: click~=8.1; extra == "dev"
Requires-Dist: matplotlib<=3.9.2,>=3.5.0; extra == "dev"
Requires-Dist: numpy<=2.1.3,>=1.24.3; extra == "dev"
Requires-Dist: prettytable==3.11.0; extra == "dev"
Requires-Dist: coverage>=7; extra == "dev"
Requires-Dist: coverage-badge>=1; extra == "dev"
